tads/__init__.py
tads/__main__.py
tads/actors/__init__.py
tads/actors/documents/__init__.py
tads/actors/documents/docproc.py
tads/actors/documents/utils.py
tads/core/__init__.py
tads/core/interface.py
tads-0.1.3.dist-info/WHEEL
tads-0.1.3.dist-info/METADATA
tads-0.1.3.dist-info/RECORD
